pape/__init__.py
pape/utilities.py
pape-0.1.0.dist-info/METADATA
pape-0.1.0.dist-info/WHEEL
pape-0.1.0.dist-info/licenses/LICENSE
pape-0.1.0.dist-info/RECORD
