Metadata-Version: 2.4
Name: pape
Version: 0.1.0
Summary: A package for personalized Python add-ons, created by Carter Pape
Project-URL: Homepage, https://github.com/CarterPape/pape-python-package
Project-URL: Bug Tracker, https://github.com/CarterPape/pape-python-package/issues
Author-email: Carter Pape <author@newsbot.carterpape.com>
License:                     GNU GENERAL PUBLIC LICENSE
License-File: LICENSE
Classifier: License :: OSI Approved :: GNU General Public License v3 or later (GPLv3+)
Classifier: Natural Language :: English
Classifier: Operating System :: OS Independent
Classifier: Programming Language :: Python
Requires-Python: >=3.9
Requires-Dist: tzlocal>=5.3.1
